options/__init__.py
options/callattr.py
options/chainstuf.py
options/config.py
options/core.py
options/funclike.py
options/methset.py
options/version.py
options-1.4.10.dist-info/LICENSE.txt
options-1.4.10.dist-info/METADATA
options-1.4.10.dist-info/WHEEL
options-1.4.10.dist-info/top_level.txt
options-1.4.10.dist-info/RECORD
